{"associatedCards":[],"associatedCardRefs":[],"assets":[{"gameAbsolutePath":"http://dd.b.pvp.net/1_0_0/set1/ru_ru/img/cards/01SI048T1.png","fullAbsolutePath":"http://dd.b.pvp.net/1_0_0/set1/ru_ru/img/cards/01SI048T1-full.png"}],"region":"Сумрачные острова","regionRef":"ShadowIsles","attack":4,"cost":2,"health":4,"description":"","descriptionRaw":"","levelupDescription":"","levelupDescriptionRaw":"","flavorText":"Время остановилось, а безумие осталось. ","artistName":"SIXMOREVODKA","name":"Сбежавшее отродье","cardCode":"01SI048T1","keywords":[],"keywordRefs":[],"spellSpeed":"","spellSpeedRef":"","rarity":"Нет","rarityRef":"None","subtype":"","subtypes":[],"supertype":"","type":"Боец","collectible":false}