{"associatedCards":[],"associatedCardRefs":[],"assets":[{"gameAbsolutePath":"http://dd.b.pvp.net/1_0_0/set2/ru_ru/img/cards/02SI001.png","fullAbsolutePath":"http://dd.b.pvp.net/1_0_0/set2/ru_ru/img/cards/02SI001-full.png"}],"region":"Сумрачные острова","regionRef":"ShadowIsles","attack":2,"cost":5,"health":4,"description":"Когда погибнет другой союзник, <link=keyword.Drain><style=Keyword>истощите</style></link> вражеский нексус на<br>1 ед. здоровья.","descriptionRaw":"Когда погибнет другой союзник, истощите вражеский нексус на1 ед. здоровья.","levelupDescription":"","levelupDescriptionRaw":"","flavorText":"\"…случайно встретил Нивена… новый паромщик. Он отвез нас в… кстати, он неплохо поет. Прежде чем… надо пригласить его на ужин\". – Обрывки дневниковых записей","artistName":"Kudos Productions","name":"Сборщик с Неполяны","cardCode":"02SI001","keywords":[],"keywordRefs":[],"spellSpeed":"","spellSpeedRef":"","rarity":"РЕДКИЕ","rarityRef":"Rare","subtype":"","subtypes":[],"supertype":"","type":"Боец","collectible":true}