{"associatedCards":[],"associatedCardRefs":[],"assets":[{"gameAbsolutePath":"http://dd.b.pvp.net/1_0_0/set1/it_it/img/cards/01NX024.png","fullAbsolutePath":"http://dd.b.pvp.net/1_0_0/set1/it_it/img/cards/01NX024-full.png"}],"region":"Noxus","regionRef":"Noxus","attack":5,"cost":5,"health":4,"description":"<link=vocab.Support><style=Vocab>Supporto</style></link>: Fornisci <link=keyword.Overwhelm><sprite name=Overwhelm><style=Keyword>Sopraffare</style></link> e +3|+0 al mio alleato supportato per questo turno.","descriptionRaw":"Supporto: Fornisci Sopraffare e +3|+0 al mio alleato supportato per questo turno.","levelupDescription":"","levelupDescriptionRaw":"","flavorText":"\"Shiraza è una compagna fantastica, intendo amica, perché non stiamo assolutamente uscendo insieme. Tuttavia, se uscissi con lei, vorrei augurarle buon anniversario. Grazie, questa era l'ultima domanda.\"","artistName":"SIXMOREVODKA","name":"Kato il Braccio destro","cardCode":"01NX024","keywords":[],"keywordRefs":[],"spellSpeed":"","spellSpeedRef":"","rarity":"EPICO","rarityRef":"Epic","subtype":"","subtypes":[],"supertype":"","type":"Unità","collectible":true}