{"associatedCards":[],"associatedCardRefs":["01PZ054T1"],"assets":[{"gameAbsolutePath":"http://dd.b.pvp.net/1_0_0/set1/it_it/img/cards/01PZ054.png","fullAbsolutePath":"http://dd.b.pvp.net/1_0_0/set1/it_it/img/cards/01PZ054-full.png"}],"region":"Piltover e Zaun","regionRef":"PiltoverZaun","attack":1,"cost":2,"health":4,"description":"<link=keyword.AttackSkillMark><sprite name=AttackSkillMark><style=Keyword>Attacca</style></link>: Infliggi 2 al Nexus nemico.","descriptionRaw":"Attacca: Infliggi 2 al Nexus nemico.","levelupDescription":"","levelupDescriptionRaw":"","flavorText":"\"Siamo sicuri?\"\n\"No.\"\n\"Dovevi rispondere di sì.\"\n\"Sei tu che non dovevi chiedere.\"","artistName":"SIXMOREVODKA","name":"Recluta della Ciurma Boom","cardCode":"01PZ054","keywords":[],"keywordRefs":[],"spellSpeed":"","spellSpeedRef":"","rarity":"COMUNE","rarityRef":"Common","subtype":"","subtypes":[],"supertype":"","type":"Unità","collectible":true}