{"associatedCards":[],"associatedCardRefs":["01SI002"],"assets":[{"gameAbsolutePath":"http://dd.b.pvp.net/1_0_0/set1/it_it/img/cards/01SI036.png","fullAbsolutePath":"http://dd.b.pvp.net/1_0_0/set1/it_it/img/cards/01SI036-full.png"}],"region":"Isole Ombra","regionRef":"ShadowIsles","attack":0,"cost":1,"health":0,"description":"Evoca 2 <link=card.create><style=AssociatedCard>Larve di ragno</style></link> se un alleato è morto durante questo turno.","descriptionRaw":"Evoca 2 Larve di ragno se un alleato è morto durante questo turno.","levelupDescription":"","levelupDescriptionRaw":"","flavorText":"Quella sensazione sulla pelle non è inquietante come la consapevolezza di ciò che c'è sotto.","artistName":"Kudos Productions","name":"Formicolio","cardCode":"01SI036","keywords":["Lento"],"keywordRefs":["Slow"],"spellSpeed":"Lento","spellSpeedRef":"Slow","rarity":"COMUNE","rarityRef":"Common","subtype":"","subtypes":[],"supertype":"","type":"Incantesimo","collectible":true}