{"associatedCards":[],"associatedCardRefs":[],"assets":[{"gameAbsolutePath":"http://dd.b.pvp.net/1_0_0/set2/it_it/img/cards/02IO007.png","fullAbsolutePath":"http://dd.b.pvp.net/1_0_0/set2/it_it/img/cards/02IO007-full.png"}],"region":"Ionia","regionRef":"Ionia","attack":0,"cost":7,"health":0,"description":"Un alleato lancia un nemico contro il suo Nexus, <link=vocab.Strike><style=Vocab>colpendoli</style></link> entrambi.\r\nSe il nemico sopravvive, <link=keyword.Recall><style=Keyword>richiamalo</style></link>.","descriptionRaw":"Un alleato lancia un nemico contro il suo Nexus, colpendoli entrambi.\r\nSe il nemico sopravvive, richiamalo.","levelupDescription":"","levelupDescriptionRaw":"","flavorText":"\"Il Drago deve essere scatenato, o mi consumerà dall'interno.\" - Lee Sin","artistName":"Kudos Productions","name":"Furia del dragone","cardCode":"02IO007","keywords":["Lento"],"keywordRefs":["Slow"],"spellSpeed":"Lento","spellSpeedRef":"Slow","rarity":"EPICO","rarityRef":"Epic","subtype":"","subtypes":[],"supertype":"","type":"Incantesimo","collectible":true}