{"associatedCards":[],"associatedCardRefs":[],"assets":[{"gameAbsolutePath":"http://dd.b.pvp.net/1_0_0/set1/es_es/img/cards/01FR034.png","fullAbsolutePath":"http://dd.b.pvp.net/1_0_0/set1/es_es/img/cards/01FR034-full.png"}],"region":"Freljord","regionRef":"Freljord","attack":1,"cost":6,"health":1,"description":"Cuando se me invoca, consigo +1|+1 por cada aliado que haya muerto.","descriptionRaw":"Cuando se me invoca, consigo +1|+1 por cada aliado que haya muerto.","levelupDescription":"","levelupDescriptionRaw":"","flavorText":"''La vida no se lo ha puesto fácil al viejo Bjerg. Perdió a sus compañeros en el norte; volvió meses después, pálido y diciendo sandeces. Que si bestias gigantes por aquí, que si garras enormes por allá... Pobre hombre''. - Tabernero","artistName":"SIXMOREVODKA","name":"Los resilientes","cardCode":"01FR034","keywords":["Abrumar"],"keywordRefs":["Overwhelm"],"spellSpeed":"","spellSpeedRef":"","rarity":"RARA","rarityRef":"Rare","subtype":"","subtypes":[],"supertype":"","type":"Unidad","collectible":true}