{"associatedCards":[],"associatedCardRefs":[],"assets":[{"gameAbsolutePath":"http://dd.b.pvp.net/1_0_0/set1/es_es/img/cards/01NX017.png","fullAbsolutePath":"http://dd.b.pvp.net/1_0_0/set1/es_es/img/cards/01NX017-full.png"}],"region":"Noxus","regionRef":"Noxus","attack":3,"cost":2,"health":2,"description":"<link=vocab.Support><style=Vocab>Apoyo</style></link>: Concede <link=keyword.Quick Strike><sprite name=QuickStrike><style=Keyword>Ataque rápido</style></link> al aliado al que apoye esta ronda.","descriptionRaw":"Apoyo: Concede Ataque rápido al aliado al que apoye esta ronda.","levelupDescription":"","levelupDescriptionRaw":"","flavorText":"La Legión expandió el imperio al ritmo de sus tambores. Nada podía pararlos, y nada lo consiguió.","artistName":"SIXMOREVODKA","name":"Tamborilera de la Legión","cardCode":"01NX017","keywords":[],"keywordRefs":[],"spellSpeed":"","spellSpeedRef":"","rarity":"COMÚN","rarityRef":"Common","subtype":"","subtypes":[],"supertype":"","type":"Unidad","collectible":true}