{"associatedCards":[],"associatedCardRefs":[],"assets":[{"gameAbsolutePath":"http://dd.b.pvp.net/1_0_0/set1/es_es/img/cards/01PZ051.png","fullAbsolutePath":"http://dd.b.pvp.net/1_0_0/set1/es_es/img/cards/01PZ051-full.png"}],"region":"Piltover y Zaun","regionRef":"PiltoverZaun","attack":2,"cost":5,"health":3,"description":"Todos tus hechizos y <link=keyword.Skill><sprite name=PlaySkillMark><style=Keyword>habilidades</style></link> infligen 1 de daño adicional.","descriptionRaw":"Todos tus hechizos y habilidades infligen 1 de daño adicional.","levelupDescription":"","levelupDescriptionRaw":"","flavorText":"''¿Me dices que quieres un extra de explosiones? ¡Pues has venido al lugar adecuado!''.","artistName":"SIXMOREVODKA","name":"Forjadora temeraria","cardCode":"01PZ051","keywords":[],"keywordRefs":[],"spellSpeed":"","spellSpeedRef":"","rarity":"RARA","rarityRef":"Rare","subtype":"","subtypes":[],"supertype":"","type":"Unidad","collectible":true}