{"associatedCards":[],"associatedCardRefs":[],"assets":[{"gameAbsolutePath":"http://dd.b.pvp.net/1_0_0/set1/es_es/img/cards/01SI025.png","fullAbsolutePath":"http://dd.b.pvp.net/1_0_0/set1/es_es/img/cards/01SI025-full.png"}],"region":"Islas de la Sombra","regionRef":"ShadowIsles","attack":0,"cost":6,"health":0,"description":"Mata a un aliado para infligir a cualquier unidad o estructura una cantidad de daño equivalente a su poder.","descriptionRaw":"Mata a un aliado para infligir a cualquier unidad o estructura una cantidad de daño equivalente a su poder.","levelupDescription":"","levelupDescriptionRaw":"","flavorText":"Para los que no pueden morir, matar no significada nada.","artistName":"Kudos Productions","name":"Atrocidad","cardCode":"01SI025","keywords":["Veloz"],"keywordRefs":["Fast"],"spellSpeed":"Veloz","spellSpeedRef":"Fast","rarity":"RARA","rarityRef":"Rare","subtype":"","subtypes":[],"supertype":"","type":"Hechizo","collectible":true}