{"associatedCards":[],"associatedCardRefs":[],"assets":[{"gameAbsolutePath":"http://dd.b.pvp.net/1_0_0/set2/es_es/img/cards/02BW032T1.png","fullAbsolutePath":"http://dd.b.pvp.net/1_0_0/set2/es_es/img/cards/02BW032T1-full.png"}],"region":"Aguas Estancadas","regionRef":"Bilgewater","attack":0,"cost":0,"health":1,"description":"Los barriles de pólvora se acumulan.\r\nTodos tus hechizos y habilidades infligen <style=Variable>1</style> de daño adicional.\r\nMuero cuando tu hechizo o habilidad inflige daño a enemigos.","descriptionRaw":"Los barriles de pólvora se acumulan.\r\nTodos tus hechizos y habilidades infligen 1 de daño adicional.\r\nMuero cuando tu hechizo o habilidad inflige daño a enemigos.","levelupDescription":"","levelupDescriptionRaw":"","flavorText":"\"Querer es volar por los aires\". - Refrán de Aguas Estancadas","artistName":"Kudos Productions","name":"Barril de pólvora","cardCode":"02BW032T1","keywords":["Inmóvil","Vulnerable"],"keywordRefs":["Immobile","Vulnerable"],"spellSpeed":"","spellSpeedRef":"","rarity":"Ninguna","rarityRef":"None","subtype":"","subtypes":[],"supertype":"","type":"Unidad","collectible":false}