{"associatedCards":[],"associatedCardRefs":["02PZ008","02PZ008T2"],"assets":[{"gameAbsolutePath":"http://dd.b.pvp.net/1_0_0/set2/es_es/img/cards/02PZ008T1.png","fullAbsolutePath":"http://dd.b.pvp.net/1_0_0/set2/es_es/img/cards/02PZ008T1-full.png"}],"region":"Piltover y Zaun","regionRef":"PiltoverZaun","attack":0,"cost":3,"health":0,"description":"Concede +2|+0 a un aliado esta ronda.\r\nCrea 1 <link=card.selfRef><style=AssociatedCard>Rompemuros</style></link> <link=keyword.Fleeting><sprite name=Fleeting><style=Keyword>Fugaz</style></link> en la mano.\r\nAñade 1 <link=card.level1><style=AssociatedCard>Vi</style></link> a tu mazo.","descriptionRaw":"Concede +2|+0 a un aliado esta ronda.\r\nCrea 1 Rompemuros Fugaz en la mano.\r\nAñade 1 Vi a tu mazo.","levelupDescription":"","levelupDescriptionRaw":"","flavorText":"\"Dejo que mis puños hablen por mí\". - Vi","artistName":"Kudos Productions","name":"Rompemuros de Vi","cardCode":"02PZ008T1","keywords":["Ráfaga"],"keywordRefs":["Burst"],"spellSpeed":"Ráfaga","spellSpeedRef":"Burst","rarity":"Ninguna","rarityRef":"None","subtype":"","subtypes":[],"supertype":"Campeón","type":"Hechizo","collectible":false}