{"associatedCards":[],"associatedCardRefs":[],"assets":[{"gameAbsolutePath":"http://dd.b.pvp.net/1_0_0/set1/en_us/img/cards/01DE041.png","fullAbsolutePath":"http://dd.b.pvp.net/1_0_0/set1/en_us/img/cards/01DE041-full.png"}],"region":"Demacia","regionRef":"Demacia","attack":0,"cost":6,"health":0,"description":"Give two allies +3|+3 this round.","descriptionRaw":"Give two allies +3|+3 this round.","levelupDescription":"","levelupDescriptionRaw":"","flavorText":"\"Cover me, I'm going in!\"\n\"Funny, I was about to say the same to you.\"\n- Lorn and Dax of the Eastern Battalion","artistName":"Kudos Productions","name":"Back to Back","cardCode":"01DE041","keywords":["Burst"],"keywordRefs":["Burst"],"spellSpeed":"Burst","spellSpeedRef":"Burst","rarity":"RARE","rarityRef":"Rare","subtype":"","subtypes":[],"supertype":"","type":"Spell","collectible":true}