{"associatedCards":[],"associatedCardRefs":[],"assets":[{"gameAbsolutePath":"http://dd.b.pvp.net/1_0_0/set1/en_us/img/cards/01FR053.png","fullAbsolutePath":"http://dd.b.pvp.net/1_0_0/set1/en_us/img/cards/01FR053-full.png"}],"region":"Freljord","regionRef":"Freljord","attack":3,"cost":3,"health":3,"description":"","descriptionRaw":"","levelupDescription":"","levelupDescriptionRaw":"","flavorText":"\"Ol' Longhorn here lost an eye defending the Poro King himself from an ornery wildclaw! After all, it's not the size of the hammer but the size of the heart that matters.\" - Poro Herder\n","artistName":"SIXMOREVODKA","name":"Mighty Poro","cardCode":"01FR053","keywords":["Overwhelm"],"keywordRefs":["Overwhelm"],"spellSpeed":"","spellSpeedRef":"","rarity":"COMMON","rarityRef":"Common","subtype":"PORO","subtypes":["PORO"],"supertype":"","type":"Unit","collectible":true}