{"associatedCards":[],"associatedCardRefs":["01SI048T1"],"assets":[{"gameAbsolutePath":"http://dd.b.pvp.net/1_0_0/set1/en_us/img/cards/01SI048.png","fullAbsolutePath":"http://dd.b.pvp.net/1_0_0/set1/en_us/img/cards/01SI048-full.png"}],"region":"Shadow Isles","regionRef":"ShadowIsles","attack":1,"cost":2,"health":1,"description":"<link=keyword.Last Breath><sprite name=LastBreath><style=Keyword>Last Breath</style></link>: Summon an <link=card.summon><style=AssociatedCard>Escaped Abomination</style></link>.","descriptionRaw":"Last Breath: Summon an Escaped Abomination.","levelupDescription":"","levelupDescriptionRaw":"","flavorText":"Madness and time. Never was there a more terrible pair.","artistName":"SIXMOREVODKA","name":"Cursed Keeper","cardCode":"01SI048","keywords":["Can't Block","Last Breath"],"keywordRefs":["CantBlock","LastBreath"],"spellSpeed":"","spellSpeedRef":"","rarity":"COMMON","rarityRef":"Common","subtype":"","subtypes":[],"supertype":"","type":"Unit","collectible":true}