{"associatedCards":[],"associatedCardRefs":[],"assets":[{"gameAbsolutePath":"http://dd.b.pvp.net/1_0_0/set2/en_us/img/cards/02BW020.png","fullAbsolutePath":"http://dd.b.pvp.net/1_0_0/set2/en_us/img/cards/02BW020-full.png"}],"region":"Bilgewater","regionRef":"Bilgewater","attack":0,"cost":0,"health":0,"description":"Deal 1 to the enemy Nexus.","descriptionRaw":"Deal 1 to the enemy Nexus.","levelupDescription":"","levelupDescriptionRaw":"","flavorText":"\"Yer supposed to fire w' the rest of us, lad! That's what a salvo is!\" - Petty Officer","artistName":"Kudos Productions","name":"Warning Shot","cardCode":"02BW020","keywords":["Burst"],"keywordRefs":["Burst"],"spellSpeed":"Burst","spellSpeedRef":"Burst","rarity":"COMMON","rarityRef":"Common","subtype":"","subtypes":[],"supertype":"","type":"Spell","collectible":true}