{"associatedCards":[],"associatedCardRefs":[],"assets":[{"gameAbsolutePath":"http://dd.b.pvp.net/1_0_0/set2/en_us/img/cards/02DE006T2.png","fullAbsolutePath":"http://dd.b.pvp.net/1_0_0/set2/en_us/img/cards/02DE006T2-full.png"}],"region":"Demacia","regionRef":"Demacia","attack":2,"cost":2,"health":1,"description":"","descriptionRaw":"","levelupDescription":"","levelupDescriptionRaw":"","flavorText":"Those who meet him swear they see a glimmer of something more in those sharp eyes, a shrewd intelligence that far surpasses any ordinary bird of prey. ","artistName":"SIXMOREVODKA","name":"Valor","cardCode":"02DE006T2","keywords":["Challenger","Scout"],"keywordRefs":["Challenger","Scout"],"spellSpeed":"","spellSpeedRef":"","rarity":"None","rarityRef":"None","subtype":"","subtypes":[],"supertype":"","type":"Unit","collectible":false}