{"associatedCards":[],"associatedCardRefs":[],"assets":[{"gameAbsolutePath":"http://dd.b.pvp.net/1_0_0/set1/es_mx/img/cards/01FR020.png","fullAbsolutePath":"http://dd.b.pvp.net/1_0_0/set1/es_mx/img/cards/01FR020-full.png"}],"region":"El Fréljord","regionRef":"Freljord","attack":0,"cost":4,"health":0,"description":"Inflijo 2 a TODAS las unidades.","descriptionRaw":"Inflijo 2 a TODAS las unidades.","levelupDescription":"","levelupDescriptionRaw":"","flavorText":"El alma de toda avalancha es una piedrita que no quiso quedarse quieta.","artistName":"SIXMOREVODKA","name":"Avalancha","cardCode":"01FR020","keywords":["Lento"],"keywordRefs":["Slow"],"spellSpeed":"Lento","spellSpeedRef":"Slow","rarity":"RARA","rarityRef":"Rare","subtype":"","subtypes":[],"supertype":"","type":"Hechizo","collectible":true}