{"associatedCards":[],"associatedCardRefs":[],"assets":[{"gameAbsolutePath":"http://dd.b.pvp.net/1_0_0/set1/es_mx/img/cards/01NX024.png","fullAbsolutePath":"http://dd.b.pvp.net/1_0_0/set1/es_mx/img/cards/01NX024-full.png"}],"region":"Noxus","regionRef":"Noxus","attack":5,"cost":5,"health":4,"description":"<link=vocab.Support><style=Vocab>Al apoyar</style></link>: Doy +3|+0 y <link=keyword.Overwhelm><sprite name=Overwhelm><style=Keyword>Arrollar</style></link> al aliado que apoyo en esta ronda.","descriptionRaw":"Al apoyar: Doy +3|+0 y Arrollar al aliado que apoyo en esta ronda.","levelupDescription":"","levelupDescriptionRaw":"","flavorText":"''Shiraza es una excelente novia... digo, amiga. Claro que no somos pareja; pero si lo fuéramos, buscaría la forma de desearle un feliz aniversario. Gracias, no más preguntas''.","artistName":"SIXMOREVODKA","name":"Kato el Brazo","cardCode":"01NX024","keywords":[],"keywordRefs":[],"spellSpeed":"","spellSpeedRef":"","rarity":"ÉPICA","rarityRef":"Epic","subtype":"","subtypes":[],"supertype":"","type":"Unidad","collectible":true}