{"associatedCards":[],"associatedCardRefs":[],"assets":[{"gameAbsolutePath":"http://dd.b.pvp.net/1_0_0/set1/es_mx/img/cards/01PZ014T1.png","fullAbsolutePath":"http://dd.b.pvp.net/1_0_0/set1/es_mx/img/cards/01PZ014T1-full.png"}],"region":"Piltóver y Zaun","regionRef":"PiltoverZaun","attack":5,"cost":6,"health":5,"description":"","descriptionRaw":"","levelupDescription":"","levelupDescriptionRaw":"","flavorText":"''El hardware no está en regla''. —Oficial de Inspecciones de la Agencia Piltoviana de Seguridad.","artistName":"SIXMOREVODKA","name":"Artilugio Ilegal","cardCode":"01PZ014T1","keywords":[],"keywordRefs":[],"spellSpeed":"","spellSpeedRef":"","rarity":"Ninguno","rarityRef":"None","subtype":"","subtypes":[],"supertype":"","type":"Unidad","collectible":false}