{"associatedCards":[],"associatedCardRefs":["02NX007","02NX007T1"],"assets":[{"gameAbsolutePath":"http://dd.b.pvp.net/1_0_0/set2/es_mx/img/cards/02NX007T2.png","fullAbsolutePath":"http://dd.b.pvp.net/1_0_0/set2/es_mx/img/cards/02NX007T2-full.png"}],"region":"Noxus","regionRef":"Noxus","attack":4,"cost":5,"health":7,"description":"Cuando infligimos daño al nexo enemigo fuera del combate, lanzo <link=keyword.Stun><sprite name=Stunned><style=Keyword>Aturdir</style></link> al enemigo <link=vocab.Strongest><style=Vocab>más fuerte</style></link> de la fila trasera.\r\n<link=vocab.Nexus Strike><style=Vocab>Golpe al Nexo</style></link>: Inflijo 3 de daño a todos los enemigos.","descriptionRaw":"Cuando infligimos daño al nexo enemigo fuera del combate, lanzo Aturdir al enemigo más fuerte de la fila trasera.\r\nGolpe al Nexo: Inflijo 3 de daño a todos los enemigos.","levelupDescription":"","levelupDescriptionRaw":"","flavorText":"''No hay sacrificio demasiado grande en pos de realizar mi visión de Noxus''. ","artistName":"SIXMOREVODKA","name":"Swain","cardCode":"02NX007T2","keywords":["Temible"],"keywordRefs":["Fearsome"],"spellSpeed":"","spellSpeedRef":"","rarity":"Ninguno","rarityRef":"None","subtype":"","subtypes":[],"supertype":"Campeón","type":"Unidad","collectible":false}