{"associatedCards":[],"associatedCardRefs":[],"assets":[{"gameAbsolutePath":"http://dd.b.pvp.net/1_0_0/set2/es_mx/img/cards/02SI006.png","fullAbsolutePath":"http://dd.b.pvp.net/1_0_0/set2/es_mx/img/cards/02SI006-full.png"}],"region":"Islas de la Sombra","regionRef":"ShadowIsles","attack":1,"cost":1,"health":1,"description":"Recibo +2|+2 la primera vez que un aliado muera.","descriptionRaw":"Recibo +2|+2 la primera vez que un aliado muera.","levelupDescription":"","levelupDescriptionRaw":"","flavorText":"Las criaturas de las Islas de la Sombra dejaron la sensiblería hace mucho tiempo. Todas tienen que comer.","artistName":"MAR Studio","name":"Bestia Ladrante","cardCode":"02SI006","keywords":[],"keywordRefs":[],"spellSpeed":"","spellSpeedRef":"","rarity":"COMÚN","rarityRef":"Common","subtype":"","subtypes":[],"supertype":"","type":"Unidad","collectible":true}