{"associatedCards":[],"associatedCardRefs":[],"assets":[{"gameAbsolutePath":"http://dd.b.pvp.net/1_0_0/set1/zh_tw/img/cards/01FR011.png","fullAbsolutePath":"http://dd.b.pvp.net/1_0_0/set1/zh_tw/img/cards/01FR011-full.png"}],"region":"弗雷爾卓德","regionRef":"Freljord","attack":3,"cost":2,"health":1,"description":"<link=vocab.Play><style=Vocab>出牌</style></link>：<link=keyword.Frostbite><sprite name=Frostbite><style=Keyword>凍傷</style></link>1個敵軍單位。","descriptionRaw":"出牌：凍傷1個敵軍單位。","levelupDescription":"","levelupDescriptionRaw":"","flavorText":"能夠適應嚴峻天候和冰封凍土，讓艾伐洛森人引以為傲。目光銳利的守軍更是進一步把自然地勢轉成防禦優勢。 ","artistName":"SIXMOREVODKA","name":"冰谷弓箭手","cardCode":"01FR011","keywords":[],"keywordRefs":[],"spellSpeed":"","spellSpeedRef":"","rarity":"普通","rarityRef":"Common","subtype":"","subtypes":[],"supertype":"","type":"單位","collectible":true}