{"associatedCards":[],"associatedCardRefs":[],"assets":[{"gameAbsolutePath":"http://dd.b.pvp.net/1_0_0/set1/zh_tw/img/cards/01NX037.png","fullAbsolutePath":"http://dd.b.pvp.net/1_0_0/set1/zh_tw/img/cards/01NX037-full.png"}],"region":"諾克薩斯","regionRef":"Noxus","attack":3,"cost":2,"health":1,"description":"<link=keyword.Last Breath><sprite name=LastBreath><style=Keyword>遺願</style></link>：對敵方主堡造成2點傷害。","descriptionRaw":"遺願：對敵方主堡造成2點傷害。","levelupDescription":"","levelupDescriptionRaw":"","flavorText":"諾克薩斯人從小就受到教誨，加入軍團效忠帝國就能光榮一生。不過只有少數人能獲得擔任軍團擲彈兵的殊榮。","artistName":"SIXMOREVODKA","name":"軍團擲彈兵","cardCode":"01NX037","keywords":["遺願"],"keywordRefs":["LastBreath"],"spellSpeed":"","spellSpeedRef":"","rarity":"普通","rarityRef":"Common","subtype":"","subtypes":[],"supertype":"","type":"單位","collectible":true}