{"associatedCards":[],"associatedCardRefs":["01NX038T2","01NX038T1"],"assets":[{"gameAbsolutePath":"http://dd.b.pvp.net/1_0_0/set1/zh_tw/img/cards/01NX038.png","fullAbsolutePath":"http://dd.b.pvp.net/1_0_0/set1/zh_tw/img/cards/01NX038-full.png"}],"region":"諾克薩斯","regionRef":"Noxus","attack":6,"cost":6,"health":5,"description":"","descriptionRaw":"","levelupDescription":"此牌在場上時敵方主堡生命值為10以下。","levelupDescriptionRaw":"此牌在場上時敵方主堡生命值為10以下。","flavorText":"「鋼鐵般的意志，媲美泰坦巨人的力量。特菲利安軍團沒有更優秀的將軍人選了。」——傑利科．斯溫\n","artistName":"SIXMOREVODKA","name":"達瑞斯","cardCode":"01NX038","keywords":["勢不可擋"],"keywordRefs":["Overwhelm"],"spellSpeed":"","spellSpeedRef":"","rarity":"英雄","rarityRef":"Champion","subtype":"","subtypes":[],"supertype":"英雄","type":"單位","collectible":true}