{"associatedCards":[],"associatedCardRefs":["01NX020T1","01NX020T3","01NX020T2"],"assets":[{"gameAbsolutePath":"http://dd.b.pvp.net/1_0_0/set1/zh_tw/img/cards/01NX020.png","fullAbsolutePath":"http://dd.b.pvp.net/1_0_0/set1/zh_tw/img/cards/01NX020-full.png"}],"region":"諾克薩斯","regionRef":"Noxus","attack":3,"cost":3,"health":3,"description":"<link=vocab.Play><style=Vocab>出牌</style></link>或<link=vocab.Strike><style=Vocab>打擊</style></link>：在手牌生成1張<link=card.create><style=AssociatedCard>迴旋飛斧</style></link>。","descriptionRaw":"出牌或打擊：在手牌生成1張迴旋飛斧。","levelupDescription":"此牌總計使用<link=card.create><style=AssociatedCard>迴旋飛斧</style></link><link=vocab.Strike><style=Vocab>打擊</style></link>2次<style=Variable></style>。","levelupDescriptionRaw":"此牌總計使用迴旋飛斧打擊2次。","flavorText":"「想要親筆簽名？去排隊吧，老兄。」","artistName":"SIXMOREVODKA","name":"達瑞文","cardCode":"01NX020","keywords":["快速攻擊"],"keywordRefs":["QuickStrike"],"spellSpeed":"","spellSpeedRef":"","rarity":"英雄","rarityRef":"Champion","subtype":"","subtypes":[],"supertype":"英雄","type":"單位","collectible":true}