{"associatedCards":[],"associatedCardRefs":[],"assets":[{"gameAbsolutePath":"http://dd.b.pvp.net/1_0_0/set1/zh_tw/img/cards/01NX047.png","fullAbsolutePath":"http://dd.b.pvp.net/1_0_0/set1/zh_tw/img/cards/01NX047-full.png"}],"region":"諾克薩斯","regionRef":"Noxus","attack":0,"cost":2,"health":0,"description":"對1個友軍單位造成1點傷害後，本回合給予另一個友軍單位+2|+2。","descriptionRaw":"對1個友軍單位造成1點傷害後，本回合給予另一個友軍單位+2|+2。","levelupDescription":"","levelupDescriptionRaw":"","flavorText":"「親愛的，有得就有失。我得，你失。」——弗拉迪米爾","artistName":"SIXMOREVODKA","name":"鮮血轉換","cardCode":"01NX047","keywords":["疾速"],"keywordRefs":["Burst"],"spellSpeed":"疾速","spellSpeedRef":"Burst","rarity":"普通","rarityRef":"Common","subtype":"","subtypes":[],"supertype":"","type":"法術","collectible":true}