{"associatedCards":[],"associatedCardRefs":[],"assets":[{"gameAbsolutePath":"http://dd.b.pvp.net/1_0_0/set1/zh_tw/img/cards/01SI002.png","fullAbsolutePath":"http://dd.b.pvp.net/1_0_0/set1/zh_tw/img/cards/01SI002-full.png"}],"region":"闇影島","regionRef":"ShadowIsles","attack":1,"cost":1,"health":1,"description":"","descriptionRaw":"","levelupDescription":"","levelupDescriptionRaw":"","flavorText":"「有什麼好怕的？不過就是一隻小蜘蛛。」——倒楣的貴族，薩森領主","artistName":"SIXMOREVODKA","name":"小蜘蛛","cardCode":"01SI002","keywords":[],"keywordRefs":[],"spellSpeed":"","spellSpeedRef":"","rarity":"無","rarityRef":"None","subtype":"蜘蛛","subtypes":["蜘蛛"],"supertype":"","type":"單位","collectible":false}