{"associatedCards":[],"associatedCardRefs":["01FR049T1"],"assets":[{"gameAbsolutePath":"http://dd.b.pvp.net/1_0_0/set1/ja_jp/img/cards/01FR049.png","fullAbsolutePath":"http://dd.b.pvp.net/1_0_0/set1/ja_jp/img/cards/01FR049-full.png"}],"region":"フレヨルド","regionRef":"Freljord","attack":3,"cost":2,"health":2,"description":"このユニットの召喚時<br>敵は<link=card.summon><style=AssociatedCard>ユキウサギ</style></link>を1体召喚する。","descriptionRaw":"このユニットの召喚時敵はユキウサギを1体召喚する。","levelupDescription":"","levelupDescriptionRaw":"","flavorText":"「ウサギを育てても狼にはならない」 - ウィンタークロウの諺","artistName":"SIXMOREVODKA","name":"ストーキングウルフ","cardCode":"01FR049","keywords":["チャレンジャー"],"keywordRefs":["Challenger"],"spellSpeed":"","spellSpeedRef":"","rarity":"コモン","rarityRef":"Common","subtype":"","subtypes":[],"supertype":"","type":"ユニット","collectible":true}