{"associatedCards":[],"associatedCardRefs":[],"assets":[{"gameAbsolutePath":"http://dd.b.pvp.net/1_0_0/set1/ja_jp/img/cards/01IO017.png","fullAbsolutePath":"http://dd.b.pvp.net/1_0_0/set1/ja_jp/img/cards/01IO017-full.png"}],"region":"アイオニア","regionRef":"Ionia","attack":2,"cost":1,"health":1,"description":"このユニットの召喚時<br>自身にこのラウンド中<br><link=keyword.Elusive><sprite name=Elusive><style=Keyword>イルーシブ</style></link>を付与する。","descriptionRaw":"このユニットの召喚時自身にこのラウンド中イルーシブを付与する。","levelupDescription":"","levelupDescriptionRaw":"","flavorText":"「あんなヤツ問題にもならねえ。逃げ道だけ確保してくれりゃ、儲けは山分けだ。どうだ、悪くない話だろう？」","artistName":"SIXMOREVODKA","name":"ナヴォリの盗賊","cardCode":"01IO017","keywords":[],"keywordRefs":[],"spellSpeed":"","spellSpeedRef":"","rarity":"コモン","rarityRef":"Common","subtype":"","subtypes":[],"supertype":"","type":"ユニット","collectible":true}