{"associatedCards":[],"associatedCardRefs":[],"assets":[{"gameAbsolutePath":"http://dd.b.pvp.net/1_0_0/set1/ja_jp/img/cards/01PZ056T6.png","fullAbsolutePath":"http://dd.b.pvp.net/1_0_0/set1/ja_jp/img/cards/01PZ056T6-full.png"}],"region":"ピルトーヴァー<nbsp>&<nbsp>ゾウン","regionRef":"PiltoverZaun","attack":3,"cost":3,"health":1,"description":"","descriptionRaw":"","levelupDescription":"","levelupDescriptionRaw":"","flavorText":"「最新の成果物の置き場所に中二階を選んだのは間違いだったかもしれない。ロボットのことは不安なものの、セラミック研究所から聞こえてくる悲鳴が、私の心に希望を灯してくれている！」 - ハイマーディンガーの研究記録 Vol.3","artistName":"SIXMOREVODKA","name":"Mk.3: フロアリムーバー","cardCode":"01PZ056T6","keywords":["イルーシブ"],"keywordRefs":["Elusive"],"spellSpeed":"","spellSpeedRef":"","rarity":"なし","rarityRef":"None","subtype":"テック","subtypes":["テック"],"supertype":"","type":"ユニット","collectible":false}