{"associatedCards":[],"associatedCardRefs":["02BW020"],"assets":[{"gameAbsolutePath":"http://dd.b.pvp.net/1_0_0/set2/ja_jp/img/cards/02BW011.png","fullAbsolutePath":"http://dd.b.pvp.net/1_0_0/set2/ja_jp/img/cards/02BW011-full.png"}],"region":"ビルジウォーター","regionRef":"Bilgewater","attack":3,"cost":4,"health":3,"description":"このユニットの召喚時<br>手札に<link=card.create><style=AssociatedCard>鉛の忠告</style></link>を1枚生成する。\r\n<link=vocab.Allegiance><style=Vocab>忠義</style></link>: 敵のデッキから<br>カードを1枚引く。","descriptionRaw":"このユニットの召喚時手札に鉛の忠告を1枚生成する。\r\n忠義: 敵のデッキからカードを1枚引く。","levelupDescription":"","levelupDescriptionRaw":"","flavorText":"「友達ってのは助け合うもんだろ？その鋭い眼光にピカピカのカトラス！オレはあんたが気に入ったぜ。それにしても、いいカトラスだなぁ」","artistName":"SIXMOREVODKA","name":"ペテン師ヨードル","cardCode":"02BW011","keywords":[],"keywordRefs":[],"spellSpeed":"","spellSpeedRef":"","rarity":"レア","rarityRef":"Rare","subtype":"","subtypes":[],"supertype":"","type":"ユニット","collectible":true}