{"associatedCards":[],"associatedCardRefs":[],"assets":[{"gameAbsolutePath":"http://dd.b.pvp.net/1_0_0/set2/ja_jp/img/cards/02PZ005.png","fullAbsolutePath":"http://dd.b.pvp.net/1_0_0/set2/ja_jp/img/cards/02PZ005-full.png"}],"region":"ピルトーヴァー<nbsp>&<nbsp>ゾウン","regionRef":"PiltoverZaun","attack":4,"cost":3,"health":3,"description":"このカードが引かれたラウンド中<br>このカードのコストは1減少する。","descriptionRaw":"このカードが引かれたラウンド中このカードのコストは1減少する。","levelupDescription":"","levelupDescriptionRaw":"","flavorText":"ミール巡査の頭の固さは、執行官の間で鉄板ネタとなった。ケプル巡査は何が面白いのかわからなかった。","artistName":"SIXMOREVODKA","name":"ピルトーヴァーの警邏隊","cardCode":"02PZ005","keywords":[],"keywordRefs":[],"spellSpeed":"","spellSpeedRef":"","rarity":"コモン","rarityRef":"Common","subtype":"","subtypes":[],"supertype":"","type":"ユニット","collectible":true}