{"associatedCards":[],"associatedCardRefs":[],"assets":[{"gameAbsolutePath":"http://dd.b.pvp.net/1_0_0/set1/ko_kr/img/cards/01FR013.png","fullAbsolutePath":"http://dd.b.pvp.net/1_0_0/set1/ko_kr/img/cards/01FR013-full.png"}],"region":"프렐요드","regionRef":"Freljord","attack":3,"cost":6,"health":8,"description":"피해를 버티고 생존하면<br>+3|+0을 얻습니다.","descriptionRaw":"피해를 버티고 생존하면+3|+0을 얻습니다.","levelupDescription":"","levelupDescriptionRaw":"","flavorText":"\"애쉬네 약골들이랑 난로를 같이 쓰느니 그냥 밖에서<br>얼어 죽고 말지. 하지만 그 녀석들이 온기를 원한다면<br>얼마든지 뜨겁게 만들어 주겠어.\"","artistName":"SIXMOREVODKA","name":"상흔의 어머니 브리나","cardCode":"01FR013","keywords":["압도"],"keywordRefs":["Overwhelm"],"spellSpeed":"","spellSpeedRef":"","rarity":"서사급","rarityRef":"Epic","subtype":"","subtypes":[],"supertype":"","type":"유닛","collectible":true}