{"associatedCards":[],"associatedCardRefs":[],"assets":[{"gameAbsolutePath":"http://dd.b.pvp.net/1_0_0/set1/ko_kr/img/cards/01FR025.png","fullAbsolutePath":"http://dd.b.pvp.net/1_0_0/set1/ko_kr/img/cards/01FR025-full.png"}],"region":"프렐요드","regionRef":"Freljord","attack":3,"cost":4,"health":4,"description":"소환 시 전장에 아군 포로가 하나 있으면 포로 2마리를 뽑습니다.","descriptionRaw":"소환 시 전장에 아군 포로가 하나 있으면 포로 2마리를 뽑습니다.","levelupDescription":"","levelupDescriptionRaw":"","flavorText":"포로 무리에게 필요한 건 두 가지뿐입니다. 사랑과 소속감.<br>다른 것들은 그냥 솜털일 뿐이죠.","artistName":"SIXMOREVODKA","name":"포로치기","cardCode":"01FR025","keywords":[],"keywordRefs":[],"spellSpeed":"","spellSpeedRef":"","rarity":"희귀급","rarityRef":"Rare","subtype":"","subtypes":[],"supertype":"","type":"유닛","collectible":true}