{"associatedCards":[],"associatedCardRefs":["01IO009T1"],"assets":[{"gameAbsolutePath":"http://dd.b.pvp.net/1_0_0/set1/ko_kr/img/cards/01IO039.png","fullAbsolutePath":"http://dd.b.pvp.net/1_0_0/set1/ko_kr/img/cards/01IO039-full.png"}],"region":"아이오니아","regionRef":"Ionia","attack":0,"cost":3,"health":0,"description":"아군 하나를 <link=keyword.Recall><style=Keyword>귀환</style></link>시키고<br><link=card.create><style=AssociatedCard>살아있는 그림자</style></link> 하나를<br>그 자리에 소환합니다.","descriptionRaw":"아군 하나를 귀환시키고살아있는 그림자 하나를그 자리에 소환합니다.","levelupDescription":"","levelupDescriptionRaw":"","flavorText":"눈에 보이는 적은 진짜일까요? 아니면 그림자의 장난일까요?","artistName":"Max Grecke","name":"그림자술","cardCode":"01IO039","keywords":["신속"],"keywordRefs":["Fast"],"spellSpeed":"신속","spellSpeedRef":"Fast","rarity":"일반급","rarityRef":"Common","subtype":"","subtypes":[],"supertype":"","type":"주문","collectible":true}