{"associatedCards":[],"associatedCardRefs":["01SI027T1"],"assets":[{"gameAbsolutePath":"http://dd.b.pvp.net/1_0_0/set1/ko_kr/img/cards/01SI027.png","fullAbsolutePath":"http://dd.b.pvp.net/1_0_0/set1/ko_kr/img/cards/01SI027-full.png"}],"region":"그림자 군도","regionRef":"ShadowIsles","attack":0,"cost":3,"health":0,"description":"이 라운드에 아군 셋 이상이 사망했으면 <link=card.summon><style=AssociatedCard>썩은 아귀</style></link> 하나를 소환합니다.\r\n<style=Variable></style>","descriptionRaw":"이 라운드에 아군 셋 이상이 사망했으면 썩은 아귀 하나를 소환합니다.\r\n","levelupDescription":"","levelupDescriptionRaw":"","flavorText":"\"독이빨로 무장한 네 신 앞에 무릎을 꿇어라.<br>아니, 차라리 그 앞에서 죽어라.\"<br>- 엘리스","artistName":"Kudos Productions","name":"싱싱한 제물","cardCode":"01SI027","keywords":["집중"],"keywordRefs":["Slow"],"spellSpeed":"집중","spellSpeedRef":"Slow","rarity":"희귀급","rarityRef":"Rare","subtype":"","subtypes":[],"supertype":"","type":"주문","collectible":true}