{"associatedCards":[],"associatedCardRefs":["01SI052T2","01SI052"],"assets":[{"gameAbsolutePath":"http://dd.b.pvp.net/1_0_0/set1/ko_kr/img/cards/01SI052T1.png","fullAbsolutePath":"http://dd.b.pvp.net/1_0_0/set1/ko_kr/img/cards/01SI052T1-full.png"}],"region":"그림자 군도","regionRef":"ShadowIsles","attack":4,"cost":5,"health":7,"description":"이 게임에서 처음 공격하면 덱이나 손에서 다른 챔피언 하나를 공격 준비 상태로 소환합니다.","descriptionRaw":"이 게임에서 처음 공격하면 덱이나 손에서 다른 챔피언 하나를 공격 준비 상태로 소환합니다.","levelupDescription":"","levelupDescriptionRaw":"","flavorText":"\"넌 내 거야. 영원히.\"<br>철커덩 덜커덩, 쇠사슬 소리가 들리고,<br>간수가 뒤에 서 있습니다...","artistName":"SIXMOREVODKA","name":"쓰레쉬","cardCode":"01SI052T1","keywords":["도전자"],"keywordRefs":["Challenger"],"spellSpeed":"","spellSpeedRef":"","rarity":"없음","rarityRef":"None","subtype":"","subtypes":[],"supertype":"챔피언","type":"유닛","collectible":false}