{"associatedCards":[],"associatedCardRefs":["02BW032","02BW032T2","02BW032T1","02BW032T4"],"assets":[{"gameAbsolutePath":"http://dd.b.pvp.net/1_0_0/set2/ko_kr/img/cards/02BW032T3.png","fullAbsolutePath":"http://dd.b.pvp.net/1_0_0/set2/ko_kr/img/cards/02BW032T3-full.png"}],"region":"빌지워터","regionRef":"Bilgewater","attack":6,"cost":5,"health":6,"description":"소환 시 및 <link=vocab.RoundStart><style=Vocab>라운드 시작</style></link> 시: <link=card.summon><style=AssociatedCard>화약통</style></link> 하나를 소환합니다.\r\n<link=keyword.AttackSkillMark><sprite name=AttackSkillMark><style=Keyword>공격</style></link>: 모든 적과 적 넥서스에<br>피해를 1 입힙니다.","descriptionRaw":"소환 시 및 라운드 시작 시: 화약통 하나를 소환합니다.\r\n공격: 모든 적과 적 넥서스에피해를 1 입힙니다.","levelupDescription":"","levelupDescriptionRaw":"","flavorText":"\"오랫동안 선장의 눈을 봐왔지.<br>순수한 분노만 가득했어.<br>언젠가 그가 빌지워터에 복수를 하고 말 거야.\"\n- 갑판장","artistName":"SIXMOREVODKA","name":"갱플랭크","cardCode":"02BW032T3","keywords":["압도"],"keywordRefs":["Overwhelm"],"spellSpeed":"","spellSpeedRef":"","rarity":"없음","rarityRef":"None","subtype":"","subtypes":[],"supertype":"챔피언","type":"유닛","collectible":false}