{"associatedCards":[],"associatedCardRefs":["02BW036"],"assets":[{"gameAbsolutePath":"http://dd.b.pvp.net/1_0_0/set2/ko_kr/img/cards/02BW027.png","fullAbsolutePath":"http://dd.b.pvp.net/1_0_0/set2/ko_kr/img/cards/02BW027-full.png"}],"region":"빌지워터","regionRef":"Bilgewater","attack":7,"cost":5,"health":7,"description":"소환 시 상대에게 <link=card.summon><style=AssociatedCard>황금 외뿔고래</style></link> 하나를 소환합니다.","descriptionRaw":"소환 시 상대에게 황금 외뿔고래 하나를 소환합니다.","levelupDescription":"","levelupDescriptionRaw":"","flavorText":"바다 밑에 반짝이는 황금은 금화도, 주괴도 아닙니다.<br>학살 함대 함장의 숙적에게 달린 반짝이는 뿔입니다.","artistName":"SIXMOREVODKA","name":"사냥 함대","cardCode":"02BW027","keywords":[],"keywordRefs":[],"spellSpeed":"","spellSpeedRef":"","rarity":"일반급","rarityRef":"Common","subtype":"","subtypes":[],"supertype":"","type":"유닛","collectible":true}