{"associatedCards":[],"associatedCardRefs":[],"assets":[{"gameAbsolutePath":"http://dd.b.pvp.net/1_0_0/set1/pt_br/img/cards/01IO006.png","fullAbsolutePath":"http://dd.b.pvp.net/1_0_0/set1/pt_br/img/cards/01IO006-full.png"}],"region":"Ionia","regionRef":"Ionia","attack":2,"cost":2,"health":1,"description":"Ao invocar um aliado, me conceda +1|+0 nesta rodada.","descriptionRaw":"Ao invocar um aliado, me conceda +1|+0 nesta rodada.","levelupDescription":"","levelupDescriptionRaw":"","flavorText":"\"Ei, cuidado com os galhos! Esquerda, ESQUERDA!\" \n\"Quando eu estiver nos SEUS ombros, Felpudinho, podemos ir pra onde você quiser. Até lá, quem decide sou eu!\"","artistName":"SIXMOREVODKA","name":"Dupla da Clareira Verdejante","cardCode":"01IO006","keywords":["Elusivo"],"keywordRefs":["Elusive"],"spellSpeed":"","spellSpeedRef":"","rarity":"RARA","rarityRef":"Rare","subtype":"","subtypes":[],"supertype":"","type":"Unidade","collectible":true}