{"associatedCards":[],"associatedCardRefs":[],"assets":[{"gameAbsolutePath":"http://dd.b.pvp.net/1_0_0/set1/pt_br/img/cards/01NX030.png","fullAbsolutePath":"http://dd.b.pvp.net/1_0_0/set1/pt_br/img/cards/01NX030-full.png"}],"region":"Noxus","regionRef":"Noxus","attack":2,"cost":2,"health":3,"description":"Quando eu sobreviver a dano, cause 2 de dano ao Nexus inimigo.","descriptionRaw":"Quando eu sobreviver a dano, cause 2 de dano ao Nexus inimigo.","levelupDescription":"","levelupDescriptionRaw":"","flavorText":"\"Edvin! Aí está você, bonitão. Estava pensando em você agorinha!\" \"Oh, então vamos juntos.\" \"Não se preocupe, eu te acompanho.\" \"Gostei! Ou quem sabe não usar nada?\"","artistName":"SIXMOREVODKA","name":"Discípula Carmesim","cardCode":"01NX030","keywords":[],"keywordRefs":[],"spellSpeed":"","spellSpeedRef":"","rarity":"RARA","rarityRef":"Rare","subtype":"","subtypes":[],"supertype":"","type":"Unidade","collectible":true}