{"associatedCards":[],"associatedCardRefs":[],"assets":[{"gameAbsolutePath":"http://dd.b.pvp.net/1_0_0/set1/pt_br/img/cards/01SI026.png","fullAbsolutePath":"http://dd.b.pvp.net/1_0_0/set1/pt_br/img/cards/01SI026-full.png"}],"region":"Ilhas das Sombras","regionRef":"ShadowIsles","attack":1,"cost":1,"health":1,"description":"<link=keyword.Last Breath><sprite name=LastBreath><style=Keyword>Suspiro Final</style></link>: Crie na mão outro seguidor com <link=keyword.Last Breath><sprite name=LastBreath><style=Keyword>Suspiro Final</style></link> de qualquer Região e com 3 ou menos de custo.","descriptionRaw":"Suspiro Final: Crie na mão outro seguidor com Suspiro Final de qualquer Região e com 3 ou menos de custo.","levelupDescription":"","levelupDescriptionRaw":"","flavorText":"Ele prendeu a respiração o máximo que pôde, rezando para que o Guardião fosse embora. Mal sabia ele que a perseguição era só o começo do tormento que fazia Thresh se deleitar...","artistName":"SIXMOREVODKA","name":"Presa do Guardião","cardCode":"01SI026","keywords":["Suspiro Final"],"keywordRefs":["LastBreath"],"spellSpeed":"","spellSpeedRef":"","rarity":"COMUM","rarityRef":"Common","subtype":"","subtypes":[],"supertype":"","type":"Unidade","collectible":true}