{"associatedCards":[],"associatedCardRefs":["02IO006T3","02IO006T1","02IO006T2"],"assets":[{"gameAbsolutePath":"http://dd.b.pvp.net/1_0_0/set2/pt_br/img/cards/02IO006.png","fullAbsolutePath":"http://dd.b.pvp.net/1_0_0/set2/pt_br/img/cards/02IO006-full.png"}],"region":"Ionia","regionRef":"Ionia","attack":3,"cost":6,"health":6,"description":"Ao conjurar um feitiço, me conceda <link=keyword.Challenger><sprite name=Challenger><style=Keyword>Desafiador</style></link> nesta rodada.\r\nSe conjurar outro, me conceda <link=keyword.Barrier><sprite name=Barrier><style=Keyword>Barreira</style></link>.","descriptionRaw":"Ao conjurar um feitiço, me conceda Desafiador nesta rodada.\r\nSe conjurar outro, me conceda Barreira.","levelupDescription":"Quando você tiver conjurado 7+ feitiços nesta partida<style=Variable></style>.","levelupDescriptionRaw":"Quando você tiver conjurado 7+ feitiços nesta partida.","flavorText":"\"O Dragão ajuda os dignos. Aos cansados, ele dá vigor. Aos enfermos, conforto. Aos perdidos, a luz. Aos abalados, o equilíbrio...\"","artistName":"SIXMOREVODKA","name":"Lee Sin","cardCode":"02IO006","keywords":["Imbuir"],"keywordRefs":["Imbue"],"spellSpeed":"","spellSpeedRef":"","rarity":"Campeão","rarityRef":"Champion","subtype":"","subtypes":[],"supertype":"Campeão","type":"Unidade","collectible":true}