{"associatedCards":[],"associatedCardRefs":[],"assets":[{"gameAbsolutePath":"http://dd.b.pvp.net/1_0_0/set1/fr_fr/img/cards/01DE016.png","fullAbsolutePath":"http://dd.b.pvp.net/1_0_0/set1/fr_fr/img/cards/01DE016-full.png"}],"region":"Demacia","regionRef":"Demacia","attack":3,"cost":3,"health":3,"description":"","descriptionRaw":"","levelupDescription":"","levelupDescriptionRaw":"","flavorText":"Le Détachement hardi se compose des plus grands guerriers d'élite de Demacia. Chacun d'eux est une légende vivante dans son village. Toutefois, tous aimeraient que leur nom soit connu dans le royaume entier.","artistName":"SIXMOREVODKA","name":"Détachement hardi","cardCode":"01DE016","keywords":[],"keywordRefs":[],"spellSpeed":"","spellSpeedRef":"","rarity":"Aucune","rarityRef":"None","subtype":"ÉLITE","subtypes":["ÉLITE"],"supertype":"","type":"Unité","collectible":false}