{"associatedCards":[],"associatedCardRefs":[],"assets":[{"gameAbsolutePath":"http://dd.b.pvp.net/1_0_0/set1/fr_fr/img/cards/01NX052.png","fullAbsolutePath":"http://dd.b.pvp.net/1_0_0/set1/fr_fr/img/cards/01NX052-full.png"}],"region":"Noxus","regionRef":"Noxus","attack":0,"cost":2,"health":0,"description":"Infligez 1 pt<style=Parentheses>(s)</style> de dégâts à un adepte allié. S'il survit, créez-en une copie en main.","descriptionRaw":"Infligez 1 pt(s) de dégâts à un adepte allié. S'il survit, créez-en une copie en main.","levelupDescription":"","levelupDescriptionRaw":"","flavorText":"Rien n'est plus salissant que la première leçon d'un hémomancien.","artistName":"Kudos Productions","name":"Sang pour sang","cardCode":"01NX052","keywords":["Rapide"],"keywordRefs":["Fast"],"spellSpeed":"Rapide","spellSpeedRef":"Fast","rarity":"COMMUN","rarityRef":"Common","subtype":"","subtypes":[],"supertype":"","type":"Sort","collectible":true}