{"associatedCards":[],"associatedCardRefs":[],"assets":[{"gameAbsolutePath":"http://dd.b.pvp.net/1_0_0/set2/fr_fr/img/cards/02BW055.png","fullAbsolutePath":"http://dd.b.pvp.net/1_0_0/set2/fr_fr/img/cards/02BW055-full.png"}],"region":"Bilgewater","regionRef":"Bilgewater","attack":4,"cost":3,"health":3,"description":"<link=vocab.Plunder><style=Vocab>Pillage</style></link> : octroyez +1|+0 aux alliés d'un coût de 1 <link=vocab.Everywhere><style=Vocab>où qu'ils soient</style></link>.","descriptionRaw":"Pillage : octroyez +1|+0 aux alliés d'un coût de 1 où qu'ils soient.","levelupDescription":"","levelupDescriptionRaw":"","flavorText":"Une fois les tirs lancés, les crochets doivent faire vite. Une eau pleine de sang attire de nombreux curieux... Et aucun d'entre eux n'est le bienvenu.","artistName":"JiHun Lee","name":"Harponneuse sanguinaire","cardCode":"02BW055","keywords":[],"keywordRefs":[],"spellSpeed":"","spellSpeedRef":"","rarity":"ÉPIQUE","rarityRef":"Epic","subtype":"","subtypes":[],"supertype":"","type":"Unité","collectible":true}