{"associatedCards":[],"associatedCardRefs":["02BW026","02BW026T3"],"assets":[{"gameAbsolutePath":"http://dd.b.pvp.net/1_0_0/set2/fr_fr/img/cards/02BW026T1.png","fullAbsolutePath":"http://dd.b.pvp.net/1_0_0/set2/fr_fr/img/cards/02BW026T1-full.png"}],"region":"Bilgewater","regionRef":"Bilgewater","attack":0,"cost":3,"health":0,"description":"Placez 1 carte de votre main dans votre deck pour piocher 3 cartes <link=keyword.Fleeting><sprite name=Fleeting><style=Keyword>fugaces</style></link> au <link=vocab.RoundStart><style=Vocab>début du prochain round</style></link>.\r\nPlacez 1 <link=card.level1><style=AssociatedCard>Twisted Fate</style></link> dans votre deck.","descriptionRaw":"Placez 1 carte de votre main dans votre deck pour piocher 3 cartes fugaces au début du prochain round.\r\nPlacez 1 Twisted Fate dans votre deck.","levelupDescription":"","levelupDescriptionRaw":"","flavorText":"«<nbsp>Je crée mon propre chemin.<nbsp>» -<nbsp>Twisted Fate","artistName":"Kudos Productions","name":"Bonne pioche de Twisted Fate","cardCode":"02BW026T1","keywords":["Instantané"],"keywordRefs":["Burst"],"spellSpeed":"Instantané","spellSpeedRef":"Burst","rarity":"Aucune","rarityRef":"None","subtype":"","subtypes":[],"supertype":"Champion","type":"Sort","collectible":false}