{"associatedCards":[],"associatedCardRefs":[],"assets":[{"gameAbsolutePath":"http://dd.b.pvp.net/1_0_0/set2/fr_fr/img/cards/02BW031.png","fullAbsolutePath":"http://dd.b.pvp.net/1_0_0/set2/fr_fr/img/cards/02BW031-full.png"}],"region":"Bilgewater","regionRef":"Bilgewater","attack":0,"cost":6,"health":0,"description":"Infligez 2 pt<style=Parentheses>(s)</style> de dégâts à une unité ennemie.\r\nSi le coup est fatal, infligez 4 pt<style=Parentheses>(s)</style> de dégâts au Nexus ennemi.","descriptionRaw":"Infligez 2 pt(s) de dégâts à une unité ennemie.\r\nSi le coup est fatal, infligez 4 pt(s) de dégâts au Nexus ennemi.","levelupDescription":"","levelupDescriptionRaw":"","flavorText":"«<nbsp>C'est moi la plus rapide.<nbsp>» -<nbsp>Miss Fortune","artistName":"Kudos Productions","name":"Double dose","cardCode":"02BW031","keywords":["Rapide"],"keywordRefs":["Fast"],"spellSpeed":"Rapide","spellSpeedRef":"Fast","rarity":"RARE","rarityRef":"Rare","subtype":"","subtypes":[],"supertype":"","type":"Sort","collectible":true}