{"associatedCards":[],"associatedCardRefs":[],"assets":[{"gameAbsolutePath":"http://dd.b.pvp.net/1_0_0/set2/fr_fr/img/cards/02IO001.png","fullAbsolutePath":"http://dd.b.pvp.net/1_0_0/set2/fr_fr/img/cards/02IO001-full.png"}],"region":"Ionia","regionRef":"Ionia","attack":3,"cost":2,"health":2,"description":"Invoquez-moi depuis votre main après avoir lancé 2 sorts lors de ce round.","descriptionRaw":"Invoquez-moi depuis votre main après avoir lancé 2 sorts lors de ce round.","levelupDescription":"","levelupDescriptionRaw":"","flavorText":"«<nbsp>L'élève doit écouter avec attention, car le dragon a rugi les premiers sons et a béni nos jeunes esprits du don de la magie.<nbsp>» -<nbsp>Enseignements du dragon","artistName":"SIXMOREVODKA","name":"Griffes du dragon","cardCode":"02IO001","keywords":[],"keywordRefs":[],"spellSpeed":"","spellSpeedRef":"","rarity":"COMMUN","rarityRef":"Common","subtype":"","subtypes":[],"supertype":"","type":"Unité","collectible":true}