{"associatedCards":[],"associatedCardRefs":[],"assets":[{"gameAbsolutePath":"http://dd.b.pvp.net/1_0_0/set1/tr_tr/img/cards/01FR003.png","fullAbsolutePath":"http://dd.b.pvp.net/1_0_0/set1/tr_tr/img/cards/01FR003-full.png"}],"region":"Freljord","regionRef":"Freljord","attack":2,"cost":2,"health":1,"description":"<link=keyword.Last Breath><sprite name=LastBreath><style=Keyword>Son Nefes</style></link>: 1 kart çekersin.","descriptionRaw":"Son Nefes: 1 kart çekersin.","levelupDescription":"","levelupDescriptionRaw":"","flavorText":"''Gençliğimde kendime uzak savaş meydanlarında yer aradım. Meğerse yerim memleketimmiş, kendi soyumun yanıymış. Artık gözlerimi, onları korumak için kullanıyorum.''","artistName":"SIXMOREVODKA","name":"Avarosa Gözcüsü","cardCode":"01FR003","keywords":["Son Nefes"],"keywordRefs":["LastBreath"],"spellSpeed":"","spellSpeedRef":"","rarity":"YAYGIN","rarityRef":"Common","subtype":"","subtypes":[],"supertype":"","type":"Birim","collectible":true}