{"associatedCards":[],"associatedCardRefs":[],"assets":[{"gameAbsolutePath":"http://dd.b.pvp.net/1_0_0/set1/tr_tr/img/cards/01IO019.png","fullAbsolutePath":"http://dd.b.pvp.net/1_0_0/set1/tr_tr/img/cards/01IO019-full.png"}],"region":"Ionia","regionRef":"Ionia","attack":1,"cost":1,"health":2,"description":"Bir dost birim <link=keyword.Barrier><sprite name=Barrier><style=Keyword>Bariyer</style></link> aldığında +2|+0 kazanırım.","descriptionRaw":"Bir dost birim Bariyer aldığında +2|+0 kazanırım.","levelupDescription":"","levelupDescriptionRaw":"","flavorText":"''Bu kır, sakinlerini korur. Ama sen, sen buralı değilsin.''","artistName":"SIXMOREVODKA","name":"Yeşilkırlı Muhafız","cardCode":"01IO019","keywords":[],"keywordRefs":[],"spellSpeed":"","spellSpeedRef":"","rarity":"YAYGIN","rarityRef":"Common","subtype":"","subtypes":[],"supertype":"","type":"Birim","collectible":true}