{"associatedCards":[],"associatedCardRefs":[],"assets":[{"gameAbsolutePath":"http://dd.b.pvp.net/1_0_0/set1/tr_tr/img/cards/01NX010.png","fullAbsolutePath":"http://dd.b.pvp.net/1_0_0/set1/tr_tr/img/cards/01NX010-full.png"}],"region":"Noxus","regionRef":"Noxus","attack":4,"cost":5,"health":4,"description":"Çağrıldığımda, bu oyunda <link=keyword.Stun><sprite name=Stunned><style=Keyword>Sersemlettiğin</style></link> ya da <link=keyword.Recall><style=Keyword>Geri Gönderdiğin</style></link> her birim için +1|+1 kazanırım. <style=Variable></style>","descriptionRaw":"Çağrıldığımda, bu oyunda Sersemlettiğin ya da Geri Gönderdiğin her birim için +1|+1 kazanırım. ","levelupDescription":"","levelupDescriptionRaw":"","flavorText":"Tüm Noxus'lular üç Kuvvet İlkesi'ni bilir. Fakat orduda yükselmek isteyen askerler bunların üçünde de ustalaşmalıdır.","artistName":"SIXMOREVODKA","name":"Lejyon Generali","cardCode":"01NX010","keywords":["Korkunç"],"keywordRefs":["Fearsome"],"spellSpeed":"","spellSpeedRef":"","rarity":"YAYGIN","rarityRef":"Common","subtype":"","subtypes":[],"supertype":"","type":"Birim","collectible":true}